loveliness/__init__.py
loveliness-0.0.1.dist-info/LICENSE
loveliness-0.0.1.dist-info/WHEEL
loveliness-0.0.1.dist-info/METADATA
loveliness-0.0.1.dist-info/RECORD
